liquid_jsonpath/__about__.py
liquid_jsonpath/__init__.py
liquid_jsonpath/default.py
liquid_jsonpath/env.py
liquid_jsonpath/py.typed
liquid_jsonpath/filters/__init__.py
liquid_jsonpath/filters/find.py
liquid_jsonpath/tags/__init__.py
liquid_jsonpath/tags/for_tag.py
liquid_jsonpath-0.2.0.dist-info/METADATA
liquid_jsonpath-0.2.0.dist-info/WHEEL
liquid_jsonpath-0.2.0.dist-info/licenses/LICENSE.txt
liquid_jsonpath-0.2.0.dist-info/RECORD
