Metadata-Version: 2.1
Name: liquid-jsonpath
Version: 0.2.0
Summary: JSONPath selectors for Python Liquid.
Project-URL: Documentation, https://jg-rp.github.io/liquid/jsonpath/introduction
Project-URL: Issues, https://github.com/jg-rp/liquid-jsonpath/issues
Project-URL: Source, https://github.com/jg-rp/liquid-jsonpath
Author-email: James Prior <jamesgr.prior@gmail.com>
License-Expression: MIT
License-File: LICENSE.txt
Classifier: Development Status :: 4 - Beta
Classifier: Intended Audience :: Developers
Classifier: License :: OSI Approved :: MIT License
Classifier: Programming Language :: Python
Classifier: Programming Language :: Python :: 3.7
Classifier: Programming Language :: Python :: 3.8
Classifier: Programming Language :: Python :: 3.9
Classifier: Programming Language :: Python :: 3.10
Classifier: Programming Language :: Python :: 3.11
Classifier: Programming Language :: Python :: Implementation :: CPython
Classifier: Programming Language :: Python :: Implementation :: PyPy
Requires-Python: >=3.7
Requires-Dist: python-jsonpath>=0.7.1
Requires-Dist: python-liquid>=1.9.2
